{
	"configurations" : 
	[
		{
			"directories" : 
			[
				{
					"build" : ".",
					"hasInstallRule" : true,
					"jsonFile" : "directory-.-Debug-909ca9e0c0024113edb0.json",
					"minimumCMakeVersion" : 
					{
						"string" : "3.5"
					},
					"projectIndex" : 0,
					"source" : ".",
					"targetIndexes" : 
					[
						0
					]
				}
			],
			"name" : "Debug",
			"projects" : 
			[
				{
					"directoryIndexes" : 
					[
						0
					],
					"name" : "luminar",
					"targetIndexes" : 
					[
						0
					]
				}
			],
			"targets" : 
			[
				{
					"directoryIndex" : 0,
					"id" : "luminar::@6890427a1f51a3e7e1df",
					"jsonFile" : "target-luminar-Debug-5964721fd965a17a9ccf.json",
					"name" : "luminar",
					"projectIndex" : 0
				}
			]
		}
	],
	"kind" : "codemodel",
	"paths" : 
	{
		"build" : "C:/Users/Fablur/Desktop/Projects/luminar/build",
		"source" : "C:/Users/Fablur/Desktop/Projects/luminar"
	},
	"version" : 
	{
		"major" : 2,
		"minor" : 6
	}
}
